[
 {
  "index": 60387,
  "word": "TRANSFLUENT",
  "def": "Passing or flowing through a bridge; -- said of water. Wright."
 },
 {
  "index": 1074,
  "word": "HYPOSKELETAL",
  "def": "Beneath the endoskeleton; hypaxial; as, the hyposkeletalmuscles; -- opposed to episkeletal."
 },
 {
  "index": 22725,
  "word": "SHRIVALTY",
  "def": "Shrievalty. Johnson."
 },
 {
  "index": 30302,
  "word": "CULL",
  "def": "To separate, select, or pick out; to choose and gather orcollect; as, to cuil flowers.From his herd he culls, For slaughter, from the fairest of his bulls.Dryden.Whitest honey in fairy gardens culled. Tennyson."
 },
 {
  "index": 14245,
  "word": "WELL-MEANER",
  "def": "One whose intention is good. \"Well-meaners think no harm.\"Dryden."
 },
 {
  "index": 63808,
  "word": "MENDER",
  "def": "One who mends or repairs."
 },
 {
  "index": 56257,
  "word": "UNCONFORMABILITY",
  "def": "Want of parallelism between one series of strata and another,especially when due to a disturbance of the position of the earlierstrata before the latter were deposited."
 },
 {
  "index": 55103,
  "word": "ROTUND",
  "def": "orbicular, or nearly so. Gray."
 },
 {
  "index": 21747,
  "word": "SPERAGE",
  "def": "Asperagus. [Obs.] Sylvester."
 },
 {
  "index": 72365,
  "word": "DEMOCRATICALLY",
  "def": "In a democratic manner."
 },
 {
  "index": 76360,
  "word": "PASQUINADE",
  "def": "A lampoon or satirical writing. Macaulay."
 },
 {
  "index": 33800,
  "word": "APLASTIC",
  "def": "Not plastic or easily molded."
 }
]