[
 {
  "index": 42650,
  "word": "CAR WHEEL",
  "def": "A flanged wheel of a railway car or truck."
 },
 {
  "index": 22013,
  "word": "DEMIURGIC",
  "def": "Pertaining to a demiurge; formative; creative. \"Demiurgicpower.\" De Quincey."
 },
 {
  "index": 53566,
  "word": "SYCOPHANTRY",
  "def": "Sycophancy. [Obs.]"
 },
 {
  "index": 28,
  "word": "OTHERNESS",
  "def": "The quality or state of being other or different; alterity;oppositeness."
 },
 {
  "index": 71969,
  "word": "LONGE",
  "def": "Same as 4th Lunge."
 },
 {
  "index": 51303,
  "word": "AMID",
  "def": "See Amidst."
 },
 {
  "index": 48342,
  "word": "CORYPHEE",
  "def": "A ballet dancer."
 },
 {
  "index": 81410,
  "word": "CONCLUSIBLE",
  "def": "Demonstrable; determinable. [Obs.] Hammond."
 },
 {
  "index": 46981,
  "word": "MULTIPLICABLE",
  "def": "Capable of being multiplied; multipliable."
 },
 {
  "index": 78103,
  "word": "VISITING",
  "def": "a. \u0026 vb. n. from Visit. Visiting ant. (Zoöl.) See Driver ant,under Driver.-- Visiting book, a book in which a record of visits received, made,and to be made, is kept. Thackeray.-- Visiting card. See under Card."
 },
 {
  "index": 72895,
  "word": "ECONOMIZATION",
  "def": "The act or practice of using to the best effect. [R.] H.Spenser."
 },
 {
  "index": 6219,
  "word": "NAG",
  "def": "To tease in a petty way; to scold habitually; to annoy; to fretpertinaciously. [Colloq.] \"She never nagged.\" J. Ingelow."
 }
]