[
 {
  "index": 45590,
  "word": "DULCAMARA",
  "def": "A plant (Solanum Dulcamara). See Bittersweet, n.,"
 },
 {
  "index": 47158,
  "word": "SLURRED",
  "def": "Marked with a slur; performed in a smooth, gliding style, likenotes marked with a slur."
 },
 {
  "index": 6677,
  "word": "STREPSIPTERA",
  "def": "A group of small insects having the anterior wings rudimentary,and in the form of short and slender twisted appendages, while theposterior ones are large and membranous. They are parasitic in thelarval state on bees, wasps, and the like; -- called also Rhipiptera.See Illust. under Rhipipter."
 },
 {
  "index": 7571,
  "word": "CUCULOID",
  "def": "Like or belonging to the cuckoos (Cuculidæ)."
 },
 {
  "index": 11180,
  "word": "UNMASCULATE",
  "def": "To emasculate. [Obs.] Fuller."
 },
 {
  "index": 39337,
  "word": "DISADVENTURE",
  "def": "Misfortune; mishap. [Obs.] Sir W. Raleigh."
 },
 {
  "index": 77692,
  "word": "IDIOPHANOUS",
  "def": "Exhibiting interference figures without the aid of apolariscope, as certain crystals."
 },
 {
  "index": 37527,
  "word": "WALKYR",
  "def": "See Valkyria."
 },
 {
  "index": 18111,
  "word": "ZEUGLODONT",
  "def": "Any species of Zeuglodonta."
 },
 {
  "index": 31827,
  "word": "CISCO",
  "def": "The Lake herring (Coregonus Artedi), valuable food fish of theGreat Lakes of North America. The name is also applied to C. Hoyi, arelated species of Lake Michigan."
 },
 {
  "index": 68161,
  "word": "RAJA",
  "def": "Same as Rajah."
 },
 {
  "index": 67988,
  "word": "ANISOPODA",
  "def": "A division of Crustacea, which, in some its characteristics, isintermediate between Amphipoda and Isopoda."
 }
]