[
 {
  "index": 16612,
  "word": "TRANSFORMABLE",
  "def": "Capable of being transformed or changed."
 },
 {
  "index": 74178,
  "word": "HENDECASYLLABLE",
  "def": "A metrical line of eleven syllables. J. Warton."
 },
 {
  "index": 22235,
  "word": "BLAZER",
  "def": "One who spreads reports or blazes matters abroad. \"Blazers ofcrime.\" Spenser."
 },
 {
  "index": 58479,
  "word": "AFFLUXION",
  "def": "The act of flowing towards; afflux. Sir T. Browne."
 },
 {
  "index": 19256,
  "word": "IMMOLATOR",
  "def": "One who offers in sacrifice; specifically, one of a sect ofRussian fanatics who practice self-mutilatio and sacrifice."
 },
 {
  "index": 57010,
  "word": "SEISMOGRAPHIC",
  "def": "Of or pertaining to a seismograph; indicated by a seismograph."
 },
 {
  "index": 85948,
  "word": "OBLIGING",
  "def": "Putting under obligation; disposed to oblige or do favors;hence, helpful; civil; kind.Mons.Strozzi has many curiosities, and is very obliging to a strangerwho desires the sight of them. Addison."
 },
 {
  "index": 40295,
  "word": "SALOGEN",
  "def": "A halogen. [Obs.]"
 },
 {
  "index": 25372,
  "word": "SOILY",
  "def": "Dirty; soiled. [Obs.] Fuller."
 },
 {
  "index": 21241,
  "word": "THALLATE",
  "def": "A salt of a hypothetical thallic acid."
 },
 {
  "index": 72032,
  "word": "THOROW",
  "def": "Through. [Obs.] \"Thorow bramble, pits, and floods.\" Beau. \u0026 Fl."
 },
 {
  "index": 60657,
  "word": "DECAYED",
  "def": "Fallen, as to physical or social condition; affected withdecay; rotten; as, decayed vegetation or vegetables; a decayedfortune or gentleman.-- De*cay\"ed*ness, n."
 }
]