[
 {
  "index": 75542,
  "word": "GRAMMARIANISM",
  "def": "The principles, practices, or peculiarities of grammarians.[R.]"
 },
 {
  "index": 4645,
  "word": "MUCKINESS",
  "def": "The quality of being mucky."
 },
 {
  "index": 74675,
  "word": "PSELLISM",
  "def": "Indistinct pronunciation; stammering."
 },
 {
  "index": 75836,
  "word": "CONDIGNNESS",
  "def": "Agreeableness to deserts; suitableness."
 },
 {
  "index": 29677,
  "word": "COPPERSMITH",
  "def": "One whose occupation is to manufacture copper utensils; aworker in copper."
 },
 {
  "index": 37003,
  "word": "GRAPHOTYPE",
  "def": "A process for producing a design upon a surface in relief sothat it can be printed from. Prepared chalk or oxide of zinc ispressed upon a smooth plate by a hydraulic press, and the design isdrawn upon this in a peculiar ink which hardens the surface whereverit is applied. The surface is then carefully rubbed or brushed,leaving the lines in relief."
 },
 {
  "index": 23771,
  "word": "SMOOTHING",
  "def": "fr. Smooth, v. Smoothing iron, an iron instrument with apolished face, for smoothing clothes; a sadiron; a flatiron.-- Smoothing plane, a short, finely set plane, for smoothing andfinishing work."
 },
 {
  "index": 32512,
  "word": "OBTRUDER",
  "def": "One who obtrudes. Boyle."
 },
 {
  "index": 40993,
  "word": "ZEAL",
  "def": "To be zealous. [Obs. \u0026 R.] Bacon."
 },
 {
  "index": 58983,
  "word": "SPICEBUSH",
  "def": "Spicewood."
 },
 {
  "index": 81763,
  "word": "SNATCH",
  "def": "To attempt to seize something suddenly; to catch; -- often withat; as, to snatch at a rope."
 },
 {
  "index": 54222,
  "word": "ENDIAPER",
  "def": "To decorate with a diaper pattern."
 }
]