[
 {
  "index": 6427,
  "word": "SCUNNER",
  "def": "To cause to loathe, or feel disgust at. [Scot. \u0026 Prov. Eng.]"
 },
 {
  "index": 59594,
  "word": "ANTHRACOMANCY",
  "def": "Divination by inspecting a burning coal."
 },
 {
  "index": 50533,
  "word": "SCIUROID",
  "def": "Resembling the tail of a squirrel; -- generally said ofbranches which are close and dense, or of spikes of grass likebarley."
 },
 {
  "index": 2109,
  "word": "OPOLCHENIE",
  "def": "See Army organization, above."
 },
 {
  "index": 48814,
  "word": "STALWARTNESS",
  "def": "The quality of being stalwart."
 },
 {
  "index": 78470,
  "word": "POMPADOUR",
  "def": "A crimson or pink color; also, a style of dress cut low andsquare in the neck; also, a mode of dressing the hair by drawing itstraight back from the forehead over a roll; -- so called after theMarchioness de Pompadour of France. Also much used adjectively."
 },
 {
  "index": 35450,
  "word": "RECONCILIATORY",
  "def": "Serving or tending to reconcile. Bp. Hall."
 },
 {
  "index": 19127,
  "word": "REGISTERSHIP",
  "def": "The office of a register."
 },
 {
  "index": 84136,
  "word": "TRADUCEMENT",
  "def": "The act of traducing; misrepresentation; ill-founded censure;defamation; calumny. [R.] Shak."
 },
 {
  "index": 9538,
  "word": "LAMPING",
  "def": "Shining; brilliant. [Obs.] \"Lamping eyes.\" Spenser."
 },
 {
  "index": 74418,
  "word": "ETHEREALIZATION",
  "def": "An ethereal or spiritlike state. J. H. Stirling."
 },
 {
  "index": 55718,
  "word": "INFRATEMPORAL",
  "def": "Below the temple; below the temporal bone."
 }
]