[
 {
  "index": 39256,
  "word": "GREENISH",
  "def": "Somewhat green; having a tinge of green; as, a greenish yellow.-- Green\"ish*ness, n."
 },
 {
  "index": 62594,
  "word": "EOZOIC",
  "def": "Of or pertaining to rocks or strata older than the Paleozoic,in many of which the eozoön has been found."
 },
 {
  "index": 79765,
  "word": "BREATHFUL",
  "def": "Full of breath; full of odor; fragrant. [Obs.]"
 },
 {
  "index": 30425,
  "word": "LEAPFUL",
  "def": "A basketful. [Obs.]"
 },
 {
  "index": 30565,
  "word": "CINNAMENE",
  "def": "Styrene (which was formerly called cinnamene because obtainedfrom cinnamic acid). See Styrene."
 },
 {
  "index": 53333,
  "word": "MAYBLOOM",
  "def": "The hawthorn."
 },
 {
  "index": 43647,
  "word": "CIVILIZER",
  "def": "One who, or that which, civilizes or tends to civilize."
 },
 {
  "index": 1405,
  "word": "NOYER",
  "def": "An annoyer. [Obs.] Tusser."
 },
 {
  "index": 51281,
  "word": "SUSTENTACLE",
  "def": "Sustenance. [Obs.] Dr. H. More."
 },
 {
  "index": 35541,
  "word": "COOLING",
  "def": "Adapted to cool and refresh; allaying heat. \"The coolingbrook.\" Goldsmith. Cooling card, something that dashes hopes. [Obs.]-- Cooling time (Law), such a lapse of time as ought, taking all thecircumstances of the case in view, to produce a subsiding of passionpreviously provoked. Wharton."
 },
 {
  "index": 12040,
  "word": "PULSE",
  "def": "Leguminous plants, or their seeds, as beans, pease, etc.If all the world Should, in a pet of temperance, feed on pulse.Milton."
 },
 {
  "index": 76040,
  "word": "STROBILIFORM",
  "def": "Shaped like a strobile."
 }
]